{
  "project_info": {
    "project_number": "477113955349",
    "project_id": "myanmar-teacher-platform",
    "storage_bucket": "myanmar-teacher-platform.firebasestorage.app"
  },
  "client": [
    {
      "client_info": {
        "mobilesdk_app_id": "1:477113955349:android:ab0a7bf0df03be7dc58a1c",
        "android_client_info": {
          "package_name": "com.misfit.mtp"
        }
      },
      "oauth_client": [],
      "api_key": [
        {
          "current_key": "AIzaSyC4B5-FHbn-4LDRh_XL6q1d-98iP_X2bAU"
        }
      ],
      "services": {
        "appinvite_service": {
          "other_platform_oauth_client": []
        }
      }
    }
  ],
  "configuration_version": "1"
}